{
  "category": "Custom",
  "base_standard": "Custom",
  "extensions": [],
  "access_control": "role_based",
  "security_features": [],
  "coverage": {
    "state_variables": {
      "nftOwner": "Custom state variable",
      "renter": "Custom state variable",
      "rentalDuration": "Custom state variable",
      "rentalStartTime": "Custom state variable",
      "nftTokenId": "Custom state variable",
      "isRented": "Custom state variable"
    },
    "functions": {
      "setNFTForRent": "Custom function",
      "rentNFT": "Custom function",
      "returnNFT": "Custom function",
      "withdrawNFT": "Custom function"
    },
    "events": {
      "NFTSetForRent": "Custom event",
      "NFTRented": "Custom event",
      "NFTReturned": "Custom event",
      "NFTWithdrawn": "Custom event"
    },
    "roles": {
      "owner": "Custom role",
      "renter": "Custom role"
    },
    "modifiers": {}
  },
  "validation_errors": [],
  "security_summary": "Contract Type: Custom\nClassification Confidence: 90%\nAccess Control: role_based\nSecurity Features: Standard\nImplementation: Custom from scratch\nSubtype: rental_system\n\nReasoning: The contract involves renting NFTs, which is not covered by standard NFT templates like ERC721 or ERC1155. It includes specific business logic for rental management, such as setting NFTs for rent, renting, and returning them, which requires custom implementation.",
  "imports_used": [
    "@openzeppelin/contracts/access/AccessControl.sol"
  ],
  "inheritance_chain": [
    "AccessControl"
  ],
  "is_template": false,
  "subtype": "rental_system",
  "classification": {
    "contract_type": "Custom",
    "subtype": "rental_system",
    "confidence": 0.9,
    "reasoning": "The contract involves renting NFTs, which is not covered by standard NFT templates like ERC721 or ERC1155. It includes specific business logic for rental management, such as setting NFTs for rent, renting, and returning them, which requires custom implementation.",
    "is_template": false,
    "recommended_approach": "custom"
  },
  "fixes_applied": [
    {
      "attempt": 0,
      "method": "semantic_repair",
      "description": "Fixed semantic/logic issues for custom contract",
      "errors_before": 2,
      "errors_after": 0
    }
  ]
}